PilotX/__init__.py
pilotx-0.0.0.dist-info/METADATA
pilotx-0.0.0.dist-info/WHEEL
pilotx-0.0.0.dist-info/licenses/LICENSE.txt
pilotx-0.0.0.dist-info/RECORD
