Metadata-Version: 2.4
Name: PilotX
Version: 0.0.0
Summary: Python package for PilotX
Author-email: DEZHI YU <dezhi.yu@bytedance.com>
License-File: LICENSE.txt
Classifier: Programming Language :: Python :: 3
Requires-Python: >=3.10
